{
  "Fifteen_Min": [
    0,
    0,
    0
  ],
  "Thirty_Min": [
    0,
    0,
    0
  ],
  "One_Hour": [
    0,
    0,
    0
  ],
  "Two_Hour": [
    0,
    0,
    0
  ],
  "Four_Hour": [
    0
  ],
  "Daily": [
    0,
    114.21,
    114.36,
    115.27,
    115.19,
    115.16,
    115.7,
    114.29,
    114.24,
    113.82,
    114.46,
    113.5,
    114.76,
    115.77,
    118.07,
    119.52,
    121.88,
    124.22,
    124.41,
    123.96,
    123.34,
    118.18,
    118.92,
    116.34,
    115.75,
    114.81,
    113.87,
    115.28,
    114.54,
    115.94,
    118.69,
    122.03,
    123.03,
    123.81,
    123.93,
    123.27,
    119.72,
    123.42,
    117.79,
    119.16,
    116.65,
    114.72,
    121.3,
    118.94,
    116.12,
    113.92,
    119.04,
    124.28,
    123.57,
    121.2,
    122.63,
    123.86,
    121.62,
    120.83,
    121.28,
    123.76,
    121.16,
    116.14,
    116.05,
    119.93,
    122.85,
    122.62,
    123.78,
    123.8,
    124.53,
    123.61,
    118.24,
    115.64,
    114.97,
    113.43,
    117.48,
    118.3,
    116.09,
    121.35,
    118.8,
    119.83,
    116.4,
    113.85,
    113.79,
    114.37,
    114.22,
    114.28,
    113.86,
    119.75,
    122.35,
    122.9,
    122.21,
    122.34,
    121,
    121.53,
    119.92,
    119.34,
    118.25,
    116.98,
    117.09,
    119.08
  ],
  "Weekly": [
    0
  ]
}