{
  "Fifteen_Min": [
    0
  ],
  "Thirty_Min": [
    0,
    0,
    0
  ],
  "One_Hour": [
    0,
    0,
    0
  ],
  "Two_Hour": [
    0,
    0,
    0
  ],
  "Four_Hour": [
    0,
    117.855,
    117.83,
    116.3,
    115.88
  ],
  "Daily": [
    0,
    113.25,
    113,
    112.94,
    114.39,
    116.04,
    114.22,
    114.5,
    115.87,
    115.19,
    116.66,
    117.23,
    117.66,
    113.41,
    117.97,
    118,
    118.74,
    118.96,
    118.83,
    118.41,
    118.94,
    118.51,
    116.38,
    115.9,
    119.07,
    120.09,
    120.03,
    119.52,
    120.43,
    120.88,
    121.84,
    122.06,
    121.47,
    121.34,
    121.99,
    122.05,
    122.16
  ],
  "Weekly": [
    0
  ]
}